unitofwork/__init__.py
unitofwork/interfaces.py
unitofwork/py.typed
unitofwork/sql_uow.py
unitofwork/uow.py
unitofwork-0.3.0.dist-info/licenses/LICENSE
unitofwork-0.3.0.dist-info/METADATA
unitofwork-0.3.0.dist-info/WHEEL
unitofwork-0.3.0.dist-info/top_level.txt
unitofwork-0.3.0.dist-info/RECORD
